aws_lambda_event_handler/__init__.py
aws_lambda_event_handler/exceptions.py
aws_lambda_event_handler/lambda_event_handler.py
aws_lambda_event_handler/log.py
aws_lambda_event_handler/models/__init__.py
aws_lambda_event_handler/models/sns_message.py
aws_lambda_event_handler-0.0.3.dist-info/METADATA
aws_lambda_event_handler-0.0.3.dist-info/RECORD
aws_lambda_event_handler-0.0.3.dist-info/WHEEL
aws_lambda_event_handler-0.0.3.dist-info/top_level.txt
tests/__init__.py
tests/fixtures.py
tests/test_exceptions.py
tests/test_lambda_event_handler.py
tests/models/__init__.py
tests/models/test_sns_message.py
