Metadata-Version: 2.1
Name: aws-lambda-event-handler
Version: 0.0.3
Summary: This package provides a decorator for Python Lambda functions handling AWS Lambda Event Records.
Home-page: https://github.com/Nr18/aws-lambda-event-handler
Author: Joris Conijn
Author-email: joris@conijnonline.nl
License: UNKNOWN
Platform: UNKNOWN
Classifier: Programming Language :: Python :: 3
Classifier: License :: OSI Approved :: MIT License
Classifier: Operating System :: OS Independent
